odin_sdk/__init__.py
odin_sdk/cli.py
odin_sdk/client.py
odin_sdk/enhanced.py
odin_sdk/odin_pb2.py
odin_sdk/odin_pb2.pyi
odin_sdk/plugins.py
odin_protocol-1.1.0.dist-info/METADATA
odin_protocol-1.1.0.dist-info/WHEEL
odin_protocol-1.1.0.dist-info/entry_points.txt
odin_protocol-1.1.0.dist-info/top_level.txt
odin_protocol-1.1.0.dist-info/RECORD
