Metadata-Version: 2.4
Name: odin_protocol
Version: 1.1.0
Summary: ODIN Protocol - Heuristic-Empowered Logic Rule System for AI-to-AI Communication
Home-page: https://github.com/odin-protocol/python-sdk
Author: Travis Jacob Johnson
Author-email: travjohnson831@gmail.com
License: Commercial
Project-URL: Homepage, https://odin-protocol.com
Project-URL: Documentation, https://docs.odin-protocol.com
Project-URL: Repository, https://github.com/odin-protocol/python-sdk
Project-URL: Bug Tracker, https://github.com/odin-protocol/python-sdk/issues
Project-URL: Interactive Demo, https://huggingface.co/spaces/odin-protocol/demo
Project-URL: Enterprise, https://odin-protocol.com/enterprise
Keywords: ai,artificial-intelligence,hel-rule-system,communication,protocol,ai-coordination,self-healing,rule-engine,enterprise-ai,real-time-decision,cross-model,interoperability,standardized-ai,ai-infrastructure,coordination-problem,multi-agent
Classifier: Development Status :: 5 - Production/Stable
Classifier: Intended Audience :: Developers
Classifier: License :: Other/Proprietary License
Classifier: Operating System :: OS Independent
Classifier: Programming Language :: Python :: 3
Classifier: Programming Language :: Python :: 3.8
Classifier: Programming Language :: Python :: 3.9
Classifier: Programming Language :: Python :: 3.10
Classifier: Programming Language :: Python :: 3.11
Classifier: Programming Language :: Python :: 3.12
Classifier: Topic :: Software Development :: Libraries :: Python Modules
Classifier: Topic :: Internet :: WWW/HTTP
Classifier: Topic :: Scientific/Engineering :: Artificial Intelligence
Classifier: Topic :: System :: Distributed Computing
Classifier: Topic :: Communications
Requires-Python: >=3.8
Requires-Dist: protobuf>=4.0.0
Requires-Dist: httpx>=0.24.0
Requires-Dist: asyncio
Requires-Dist: typing-extensions>=4.0.0
Provides-Extra: dev
Requires-Dist: pytest>=7.0.0; extra == "dev"
Requires-Dist: pytest-asyncio>=0.21.0; extra == "dev"
Requires-Dist: black>=22.0.0; extra == "dev"
Requires-Dist: isort>=5.0.0; extra == "dev"
Requires-Dist: mypy>=1.0.0; extra == "dev"
Requires-Dist: flake8>=5.0.0; extra == "dev"
Provides-Extra: enterprise
Requires-Dist: redis>=4.0.0; extra == "enterprise"
Requires-Dist: pydantic>=2.0.0; extra == "enterprise"
Requires-Dist: fastapi>=0.100.0; extra == "enterprise"
Requires-Dist: uvicorn>=0.23.0; extra == "enterprise"
Provides-Extra: analytics
Requires-Dist: pandas>=1.5.0; extra == "analytics"
Requires-Dist: numpy>=1.21.0; extra == "analytics"
Requires-Dist: matplotlib>=3.5.0; extra == "analytics"
Dynamic: author
Dynamic: author-email
Dynamic: classifier
Dynamic: description
Dynamic: description-content-type
Dynamic: home-page
Dynamic: keywords
Dynamic: license
Dynamic: project-url
Dynamic: provides-extra
Dynamic: requires-dist
Dynamic: requires-python
Dynamic: summary
